main/__init__.py
main/raumd.conf
main/raumd.py
main/requirements.txt
main/sequence.json
raumdeuter-0.0.7.dist-info/LICENSE
raumdeuter-0.0.7.dist-info/METADATA
raumdeuter-0.0.7.dist-info/WHEEL
raumdeuter-0.0.7.dist-info/entry_points.txt
raumdeuter-0.0.7.dist-info/top_level.txt
raumdeuter-0.0.7.dist-info/RECORD
