Metadata-Version: 2.1
Name: raumdeuter
Version: 0.0.7
Summary: .
Home-page: UNKNOWN
Author: Roman Botnari
Author-email: romanbotnari@me.com
License: Apache License, Version 2.0
Platform: UNKNOWN
Classifier: Programming Language :: Python :: 3
Classifier: Operating System :: OS Independent
Requires-Dist: argcomplete (==2.0.0)
Requires-Dist: colorama (==0.4.4)
Requires-Dist: commonmark (==0.9.1)
Requires-Dist: psutil (==5.9.0)
Requires-Dist: Pygments (==2.11.2)
Requires-Dist: rich (==11.0.0)
Requires-Dist: python-json-logger (==2.0.2)
